{
  "Parent": "Projectile",
  "Name": "weapon_angelicgun/angelgunbullet1",
  "Properties": {},
  "StaticProperties": {
    "Description": {
      "Value": {
        "classname": "ProjectileDesc",
        "properties": {
          "Radius": 2.0,
          "BoxSize": [
            0.0,
            0.0,
            0.0
          ],
          "MeshID": 0,
          "Speed": 20000.0,
          "HitMultipleTargets": true,
          "Penetrate": true,
          "Lifespan": 0.8,
          "Power": 4,
          "Damage": 100,
          "Particles": "AngelicGunBullet",
          "EnvHitParticles": "AngelicGuns1Impact"
        }
      }
    }
  },
  "Methods": [
    "onFire",
    "onCombatEffect"
  ],
  "PackageName": "weapon_angelicgun",
  "DefaultValues": {},
  "States": {}
}