{
  "Parent": "artifact/artifact_base",
  "Name": "artifact_pawn/artifact_pawn",
  "Properties": {},
  "StaticProperties": {
    "Description": {
      "Value": {
        "classname": "ItemDesc",
        "properties": {
          "AutoGrab": true,
          "GrabDistance": 30.0,
          "InventoryItemClass": "items/artifact_pawn",
          "Visual": "Pawn_Artifact",
          "Animations": {
            "classname": "AnimationList",
            "properties": {
              "Animations": [
                {
                  "classname": "AnimationDesc",
                  "properties": {
                    "Name": "OnGround",
                    "AnimationName": "Pawn_Artifact_Idle",
                    "Looping": true
                  }
                },
                {
                  "classname": "AnimationDesc",
                  "properties": {
                    "ID": 10,
                    "Name": "OnGround Effects",
                    "Looping": true,
                    "Triggers": [
                      {
                        "classname": "EffectTrigger",
                        "properties": {
                          "EffectName": "Artifact_Pawn_OnGround",
                          "IsRequired": true,
                          "NoLoop": true
                        }
                      }
                    ]
                  }
                },
                {
                  "classname": "AnimationDesc",
                  "properties": {
                    "ID": 1,
                    "Name": "OnPickup",
                    "AnimationName": "Pawn_Artifact_Spin",
                    "Triggers": [
                      {
                        "classname": "SoundTrigger",
                        "properties": {
                          "SoundID": 1
                        }
                      },
                      {
                        "classname": "EffectTrigger",
                        "properties": {
                          "TrackEffect": false,
                          "EffectName": "Artifact_Pawn_OnPickup",
                          "IsRequired": true,
                          "NoLoop": true
                        }
                      },
                      {
                        "classname": "DissolveTrigger",
                        "properties": {
                          "Duration": 45
                        }
                      }
                    ]
                  }
                }
              ]
            }
          },
          "Sounds": {
            "classname": "SoundList",
            "properties": {
              "Sounds": [
                {
                  "classname": "SoundDesc",
                  "properties": {
                    "ID": 0,
                    "Name": "OnGround",
                    "Volume": 0.7001953,
                    "Pitch": -5.0,
                    "Loop": true,
                    "Reverb": false,
                    "EnableDSP": false,
                    "FadeInTime": 1.0,
                    "FadeOutTime": 0.5,
                    "Offset": true,
                    "FollowActor": true,
                    "ExclusiveActor": true,
                    "Min": 50.0,
                    "Max": 2000.0,
                    "Priority": 50,
                    "Sounds": "Artifact_Pawn_Loop_01",
                    "Group": "artifacts"
                  }
                },
                {
                  "classname": "SoundDesc",
                  "properties": {
                    "ID": 2,
                    "Name": "OnGround Close",
                    "Volume": 0.5,
                    "Loop": true,
                    "Reverb": false,
                    "EnableDSP": false,
                    "FadeInTime": 1.0,
                    "FadeOutTime": 0.5,
                    "FollowActor": true,
                    "ExclusiveActor": true,
                    "Min": 1.0,
                    "Max": 1250.0,
                    "Sounds": "Artifact_Pawn_Loop_01",
                    "Group": "artifacts"
                  }
                },
                {
                  "classname": "SoundDesc",
                  "properties": {
                    "ID": 1,
                    "Name": "Pickup",
                    "Reverb": false,
                    "EnableDSP": false,
                    "FadeInTime": 1.0,
                    "FadeOutTime": 0.099975586,
                    "FollowActor": true,
                    "ExclusiveActor": true,
                    "Min": 3000.0,
                    "Max": 5000.0,
                    "Sounds": "Artifact_Pawn_Pickup_01",
                    "Group": "GUI max 2"
                  }
                }
              ]
            }
          }
        }
      }
    }
  },
  "Methods": [],
  "PackageName": "artifact_pawn",
  "DefaultValues": {},
  "States": {}
}