{
  "classname": "AnimationList",
  "properties": {
    "Animations": [
      {
        "classname": "AnimationDesc",
        "properties": {
          "Name": "CS_004_Shot_01",
          "AnimationName": "CS_004_Shot_01",
          "Triggers": [
            {
              "classname": "EffectTrigger",
              "properties": {
                "EffectName": "CS_004_Embers"
              }
            },
            {
              "classname": "SetPropertyTrigger",
              "properties": {
                "ObjectName": "War_Lava_Ortho_Sh04",
                "Property": "Power",
                "Value": "1"
              }
            }
          ]
        }
      },
      {
        "classname": "AnimationDesc",
        "properties": {
          "ID": 1,
          "Name": "CS_004_Shot_02",
          "AnimationName": "CS_004_Shot_02",
          "Triggers": [
            {
              "classname": "EffectTrigger",
              "properties": {
                "EffectName": "CS_004_Embers"
              }
            },
            {
              "classname": "EffectTrigger",
              "properties": {
                "EffectName": "CS_004_CC_01_Talk"
              }
            },
            {
              "classname": "EffectTrigger",
              "properties": {
                "EffectName": "CS_004_CC_02_Idle"
              }
            },
            {
              "classname": "EffectTrigger",
              "properties": {
                "EffectName": "CS_004_CC_03_Idle"
              }
            }
          ]
        }
      },
      {
        "classname": "AnimationDesc",
        "properties": {
          "ID": 2,
          "Name": "CS_004_Shot_03",
          "AnimationName": "CS_004_Shot_03",
          "Triggers": [
            {
              "classname": "EffectTrigger",
              "properties": {
                "EffectName": "CS_004_Embers"
              }
            }
          ]
        }
      },
      {
        "classname": "AnimationDesc",
        "properties": {
          "ID": 3,
          "Name": "CS_004_Shot_04",
          "AnimationName": "CS_004_Shot_04",
          "Triggers": [
            {
              "classname": "EffectTrigger",
              "properties": {
                "EffectName": "CS_004_Embers"
              }
            },
            {
              "classname": "SetPropertyTrigger",
              "properties": {
                "ObjectName": "War_Lava_Ortho_Sh04",
                "Property": "Power",
                "Value": "1"
              }
            }
          ]
        }
      },
      {
        "classname": "AnimationDesc",
        "properties": {
          "ID": 4,
          "Name": "CS_004_Shot_05",
          "AnimationName": "CS_004_Shot_05",
          "Triggers": [
            {
              "classname": "EffectTrigger",
              "properties": {
                "EffectName": "CS_004_Embers"
              }
            }
          ]
        }
      },
      {
        "classname": "AnimationDesc",
        "properties": {
          "ID": 5,
          "Name": "CS_004_Shot_06",
          "AnimationName": "CS_004_Shot_06",
          "Triggers": [
            {
              "classname": "SetPropertyTrigger",
              "properties": {
                "ObjectName": "War_Lava_Ortho_Sh04",
                "Property": "Power",
                "Value": "1.5"
              }
            },
            {
              "classname": "EffectTrigger",
              "properties": {
                "EffectName": "CS_004_CC_01_Talk"
              }
            },
            {
              "classname": "EffectTrigger",
              "properties": {
                "EffectName": "CS_004_CC_02_Idle"
              }
            }
          ]
        }
      },
      {
        "classname": "AnimationDesc",
        "properties": {
          "ID": 6,
          "Name": "CS_004_Shot_07",
          "AnimationName": "CS_004_Shot_07",
          "Triggers": [
            {
              "classname": "SetPropertyTrigger",
              "properties": {
                "ObjectName": "War_Lava_Ortho_Sh04",
                "Property": "Power",
                "Value": "0"
              }
            },
            {
              "classname": "SetPropertyTrigger",
              "properties": {
                "ObjectName": "War_Lava_Ortho_Sh07",
                "Property": "Power",
                "Value": "1.25"
              }
            }
          ]
        }
      },
      {
        "classname": "AnimationDesc",
        "properties": {
          "ID": 7,
          "Name": "CS_004_Shot_08",
          "AnimationName": "CS_004_Shot_08"
        }
      },
      {
        "classname": "AnimationDesc",
        "properties": {
          "ID": 8,
          "Name": "CS_004_Shot_09",
          "AnimationName": "CS_004_Shot_09",
          "Triggers": [
            {
              "classname": "EffectTrigger",
              "properties": {
                "EffectName": "CS_004_CC_03_Talk"
              }
            }
          ]
        }
      },
      {
        "classname": "AnimationDesc",
        "properties": {
          "ID": 9,
          "Name": "CS_004_Shot_10",
          "AnimationName": "CS_004_Shot_10",
          "Triggers": [
            {
              "classname": "EffectTrigger",
              "properties": {
                "EffectName": "CS_004_CC_01_Talk"
              }
            },
            {
              "classname": "EffectTrigger",
              "properties": {
                "EffectName": "CS_004_CC_02_Idle"
              }
            },
            {
              "classname": "SetPropertyTrigger",
              "properties": {
                "ObjectName": "War_Sh10",
                "Property": "Power",
                "Value": "1.25"
              }
            }
          ]
        }
      },
      {
        "classname": "AnimationDesc",
        "properties": {
          "ID": 10,
          "Name": "CS_004_Shot_11",
          "AnimationName": "CS_004_Shot_11",
          "Triggers": [
            {
              "classname": "SetPropertyTrigger",
              "properties": {
                "ObjectName": "War_Sh10",
                "Property": "Power",
                "Value": "0"
              }
            },
            {
              "classname": "EffectTrigger",
              "properties": {
                "EffectName": "CS_004_Shot_11"
              }
            }
          ]
        }
      },
      {
        "classname": "AnimationDesc",
        "properties": {
          "ID": 11,
          "Name": "CS_004_Shot_12",
          "AnimationName": "CS_004_Shot_12",
          "Triggers": [
            {
              "classname": "SetPropertyTrigger",
              "properties": {
                "ObjectName": "War_Lava_Ortho_Sh07",
                "Property": "Power",
                "Value": "1.5"
              }
            }
          ]
        }
      },
      {
        "classname": "AnimationDesc",
        "properties": {
          "ID": 12,
          "Name": "CS_004_Shot_13",
          "AnimationName": "CS_004_Shot_13",
          "Triggers": [
            {
              "classname": "EffectTrigger",
              "properties": {
                "EffectName": "CS_004_CC_03_Talk"
              }
            },
            {
              "classname": "EffectTrigger",
              "properties": {
                "EffectName": "CS_004_CC_01_Idle"
              }
            },
            {
              "classname": "SetPropertyTrigger",
              "properties": {
                "ObjectName": "War_Lava_Ortho_Sh07",
                "Property": "Power",
                "Value": "1.25"
              }
            }
          ]
        }
      },
      {
        "classname": "AnimationDesc",
        "properties": {
          "ID": 13,
          "Name": "CS_004_Shot_14",
          "AnimationName": "CS_004_Shot_14"
        }
      },
      {
        "classname": "AnimationDesc",
        "properties": {
          "ID": 14,
          "Name": "CS_004_Shot_15",
          "AnimationName": "CS_004_Shot_15",
          "Triggers": [
            {
              "classname": "EffectTrigger",
              "properties": {
                "EffectName": "CS_004_Shot_15"
              }
            }
          ]
        }
      },
      {
        "classname": "AnimationDesc",
        "properties": {
          "ID": 15,
          "Name": "CS_004_Shot_16",
          "AnimationName": "CS_004_Shot_16",
          "Triggers": [
            {
              "classname": "EffectTrigger",
              "properties": {
                "EffectName": "CS_004_CC_01_Talk"
              }
            },
            {
              "classname": "EffectTrigger",
              "properties": {
                "EffectName": "CS_004_CC_02_Idle"
              }
            }
          ]
        }
      },
      {
        "classname": "AnimationDesc",
        "properties": {
          "ID": 16,
          "Name": "CS_004_Shot_17",
          "AnimationName": "CS_004_Shot_17"
        }
      },
      {
        "classname": "AnimationDesc",
        "properties": {
          "ID": 17,
          "Name": "CS_004_Shot_18",
          "AnimationName": "CS_004_Shot_18",
          "Triggers": [
            {
              "classname": "EffectTrigger",
              "properties": {
                "EffectName": "CS_004_CC_02_Talk"
              }
            }
          ]
        }
      },
      {
        "classname": "AnimationDesc",
        "properties": {
          "ID": 18,
          "Name": "CS_004_Shot_19",
          "AnimationName": "CS_004_Shot_19",
          "Triggers": [
            {
              "classname": "EffectTrigger",
              "properties": {
                "EffectName": "CS_004_CC_03_Talk"
              }
            }
          ]
        }
      },
      {
        "classname": "AnimationDesc",
        "properties": {
          "ID": 19,
          "Name": "CS_004_Shot_20",
          "AnimationName": "CS_004_Shot_20",
          "Triggers": [
            {
              "classname": "SetPropertyTrigger",
              "properties": {
                "ObjectName": "War_Lava_Ortho_Sh07",
                "Property": "Power",
                "Value": "1"
              }
            }
          ]
        }
      },
      {
        "classname": "AnimationDesc",
        "properties": {
          "ID": 20,
          "Name": "CS_004_Shot_21",
          "AnimationName": "CS_004_Shot_21",
          "Triggers": [
            {
              "classname": "SetPropertyTrigger",
              "properties": {
                "ObjectName": "War_Lava_Ortho_Sh07",
                "Property": "Power",
                "Value": "1.25"
              }
            },
            {
              "classname": "SetPropertyTrigger",
              "properties": {
                "ObjectName": "War_Lava_Ortho_Sh04",
                "Property": "Power",
                "Value": "1"
              }
            },
            {
              "classname": "EffectTrigger",
              "properties": {
                "Duration": 160,
                "EffectName": "CS_004_CC_01_Idle"
              }
            },
            {
              "classname": "EffectTrigger",
              "properties": {
                "EffectName": "CS_004_CC_02_Idle"
              }
            },
            {
              "classname": "EffectTrigger",
              "properties": {
                "EffectName": "CS_004_CC_01_Talk",
                "TriggerFrame": 160
              }
            }
          ]
        }
      },
      {
        "classname": "AnimationDesc",
        "properties": {
          "ID": 21,
          "Name": "CS_004_Shot_22",
          "AnimationName": "CS_004_Shot_22",
          "Triggers": [
            {
              "classname": "SetPropertyTrigger",
              "properties": {
                "ObjectName": "War_Lava_Ortho_Sh07",
                "Property": "Power",
                "Value": "1.25"
              }
            },
            {
              "classname": "SetPropertyTrigger",
              "properties": {
                "ObjectName": "War_Lava_Ortho_Sh04",
                "Property": "Power",
                "Value": "0"
              }
            }
          ]
        }
      },
      {
        "classname": "AnimationDesc",
        "properties": {
          "ID": 22,
          "Name": "CS_004_Shot_23",
          "AnimationName": "CS_004_Shot_23",
          "Triggers": [
            {
              "classname": "EffectTrigger",
              "properties": {
                "Duration": 70,
                "EffectName": "CS_004_CC_01_Idle"
              }
            },
            {
              "classname": "EffectTrigger",
              "properties": {
                "EffectName": "CS_004_CC_01_Talk",
                "TriggerFrame": 70
              }
            }
          ]
        }
      },
      {
        "classname": "AnimationDesc",
        "properties": {
          "ID": 23,
          "Name": "CS_004_Shot_24",
          "AnimationName": "CS_004_Shot_24",
          "Triggers": [
            {
              "classname": "EffectTrigger",
              "properties": {
                "EffectName": "CS_004_CC_01_Talk"
              }
            },
            {
              "classname": "EffectTrigger",
              "properties": {
                "EffectName": "CS_004_CC_02_Idle"
              }
            },
            {
              "classname": "EffectTrigger",
              "properties": {
                "EffectName": "CS_004_CC_03_Idle"
              }
            }
          ]
        }
      }
    ]
  }
}