{
  "classname": "SoundList",
  "properties": {
    "Sounds": [
      {
        "classname": "SoundDesc",
        "properties": {
          "ID": 1,
          "Name": "block impact element 1",
          "Volume": 0.7001953,
          "Pitch": -10.0,
          "RandomPitch": 0.5,
          "Delay": 10.0,
          "FollowActor": true,
          "Min": 1.0,
          "Max": 3000.0,
          "Priority": 5,
          "Sounds": "GEN_IMP_RIC_FSHWET_1,GEN_IMP_RIC_FSHWET_2,GEN_IMP_RIC_FSHWET_3,GEN_IMP_RIC_FSHWET_4,GEN_IMP_RIC_FSHWET_5",
          "Group": "doodads"
        }
      },
      {
        "classname": "SoundDesc",
        "properties": {
          "ID": 2,
          "Name": "block impact element 2",
          "Volume": 0.75,
          "Pitch": -4.0,
          "RandomPitch": 0.5,
          "Min": 1.0,
          "Max": 3000.0,
          "Priority": 10,
          "Sounds": "bodyfall_flesh_large_water_01,bodyfall_flesh_large_water_02",
          "Group": "doodads"
        }
      },
      {
        "classname": "SoundDesc",
        "properties": {
          "ID": 3,
          "Name": "block impact element 3",
          "Volume": 0.7001953,
          "Pitch": -5.0,
          "Min": 1.0,
          "Max": 3000.0,
          "Sounds": "wicked_interactive_body_slam_3,wicked_interactive_body_slam_1,wicked_interactive_body_slam_2",
          "Group": "doodads"
        }
      }
    ]
  }
}