{
  "classname": "SoundList",
  "properties": {
    "Sounds": [
      {
        "classname": "SoundDesc",
        "properties": {
          "ID": 1,
          "Name": "floor_switch_movement",
          "Volume": 0.30004883,
          "Pitch": 5.0,
          "Stream": true,
          "Loop": true,
          "FadeInTime": 0.5,
          "FadeOutTime": 0.19995117,
          "Offset": true,
          "Min": 20.0,
          "Max": 1500.0,
          "Priority": 1,
          "Sounds": "stone_drag_loop",
          "Group": "doodads"
        }
      },
      {
        "classname": "SoundDesc",
        "properties": {
          "ID": 2,
          "Name": "floor_switch_stop",
          "Volume": 0.7001953,
          "Pitch": -4.0,
          "Min": 50.0,
          "Max": 1600.0,
          "Priority": 0,
          "Sounds": "statue_fall_in_place",
          "Group": "doodads"
        }
      }
    ]
  }
}