{
  "Parent": "base/weaponupgradeitem",
  "Name": "base/move_upgrade_backgauntlet_lv3",
  "Properties": {},
  "StaticProperties": {
    "Description": {
      "Value": {
        "classname": "base/weaponupgradegauntletitemdesc",
        "properties": {
          "RequiredUpgrade": "base/move_upgrade_backgauntlet_lv2",
          "Replaces": "base/move_upgrade_backgauntlet_lv2",
          "Category": 0,
          "SubCategory": 5,
          "Label": "$Move.TremorBackward.Title",
          "Description": "$Move.TremorBackwardLvl3.Description",
          "Instructions": "$Move.TremorBackward.Instructions",
          "MerchantIcon": "icon_move_PowerHook_256",
          "Cost": 1600,
          "Level": 3,
          "PickupIcon": "icon_move_PowerHook_256"
        }
      }
    }
  },
  "Methods": [],
  "PackageName": "base",
  "DefaultValues": {
    "Name": "Move_Upgrade_BackGauntlet_Lv3"
  },
  "States": {}
}