{
  "classname": "RegionLayer",
  "properties": {
    "Root": {
      "classname": "WorldGroup",
      "properties": {
        "Objects": [
          {
            "classname": "ic_rm01/ic_woodfencebreak_03",
            "properties": {
              "Position": [
                -32085.4,
                12786.41,
                980.6
              ],
              "ObjectID": 60,
              "RegionID": 150,
              "Name": "WoodFenceBreak_04"
            }
          },
          {
            "classname": "ic_rm01/ic_woodfencebreak_01",
            "properties": {
              "Position": [
                -32085.48,
                13088.784,
                973.6
              ],
              "ObjectID": 58,
              "RegionID": 150,
              "Name": "WoodFenceBreak_03"
            }
          },
          {
            "classname": "ic_rm01/ic_woodfencebreak_02",
            "properties": {
              "Position": [
                -32090.03,
                14614.557,
                956.63
              ],
              "ObjectID": 56,
              "RegionID": 150,
              "Name": "WoodFenceBreak_02"
            }
          },
          {
            "classname": "ic_rm01/ic_woodfencebreak_01",
            "properties": {
              "Position": [
                -32106.992,
                14886.888,
                966.63
              ],
              "ObjectID": 54,
              "RegionID": 150,
              "Name": "WoodFenceBreak_01"
            }
          },
          {
            "classname": "ic_rm01/ic_woodfencebreak_l",
            "properties": {
              "Position": [
                -32047.32,
                15911.857,
                974.626
              ],
              "ObjectID": 52,
              "RegionID": 150,
              "Name": "WoodFenceBreak_L"
            }
          },
          {
            "classname": "StaticObject",
            "properties": {
              "Position": [
                -33875.12,
                17685.2,
                1911.72
              ],
              "Rotation": [
                0.0,
                -0.0,
                0.0
              ],
              "ObjectName": "sk_ic_rm01b_upper_hclimb",
              "PackageName": "ic_rm01",
              "ObjectID": 30,
              "RegionID": 150,
              "Name": "sk_ic_rm01b_upper_hclimb",
              "LightGroup": 8193
            }
          },
          {
            "classname": "base/blocker",
            "properties": {
              "BlockType": 2,
              "Position": [
                -32078.82,
                16189.2,
                1052.4099
              ],
              "Rotation": [
                0.0,
                -0.0,
                0.0
              ],
              "Scale": [
                248.0,
                348.0,
                216.0
              ],
              "Shape": 0,
              "ObjectID": 23,
              "RegionID": 150,
              "Name": "Blocker_04"
            }
          },
          {
            "classname": "base/blocker",
            "properties": {
              "BlockType": 2,
              "Position": [
                -31985.078,
                13571.899,
                1074.34
              ],
              "Rotation": [
                0.0,
                -0.0,
                15.999987
              ],
              "Scale": [
                192.0,
                114.0,
                216.0
              ],
              "ObjectID": 22,
              "RegionID": 150,
              "Name": "Blocker_03"
            }
          },
          {
            "classname": "base/blocker",
            "properties": {
              "BlockType": 2,
              "Position": [
                -31985.078,
                14134.899,
                1074.34
              ],
              "Rotation": [
                0.0,
                0.0,
                -15.999987
              ],
              "Scale": [
                192.0,
                114.0,
                216.0
              ],
              "ObjectID": 21,
              "RegionID": 150,
              "Name": "Blocker_02"
            }
          },
          {
            "classname": "base/blocker",
            "properties": {
              "BlockType": 2,
              "Position": [
                -32041.078,
                14286.899,
                1074.34
              ],
              "Rotation": [
                0.0,
                -0.0,
                0.0
              ],
              "Scale": [
                100.0,
                348.0,
                216.0
              ],
              "Shape": 0,
              "ObjectID": 20,
              "RegionID": 150,
              "Name": "Blocker_01"
            }
          },
          {
            "classname": "base/blocker",
            "properties": {
              "BlockType": 2,
              "Position": [
                -32041.078,
                13424.899,
                1074.34
              ],
              "Rotation": [
                0.0,
                -0.0,
                0.0
              ],
              "Scale": [
                100.0,
                348.0,
                216.0
              ],
              "Shape": 0,
              "ObjectID": 19,
              "RegionID": 150,
              "Name": "Blocker"
            }
          },
          {
            "classname": "StaticObject",
            "properties": {
              "Position": [
                -33875.02,
                17685.2,
                1911.72
              ],
              "Rotation": [
                0.0,
                -0.0,
                0.0
              ],
              "ObjectName": "sk_ic_rm01b_lower",
              "PackageName": "ic_rm01",
              "ObjectID": 16,
              "RegionID": 150,
              "Name": "sk_ic_rm01b_lower"
            }
          },
          {
            "classname": "StaticObject",
            "properties": {
              "Position": [
                -33875.02,
                17685.2,
                1911.72
              ],
              "Rotation": [
                0.0,
                -0.0,
                0.0
              ],
              "ObjectName": "sk_ic_rm01b_upper",
              "PackageName": "ic_rm01",
              "ObjectID": 14,
              "RegionID": 150,
              "Name": "sk_ic_rm01b_upper"
            }
          },
          {
            "classname": "StaticObject",
            "properties": {
              "Position": [
                -33875.02,
                17685.2,
                1911.72
              ],
              "Rotation": [
                0.0,
                -0.0,
                0.0
              ],
              "ObjectName": "sk_ic_rm01a",
              "PackageName": "ic_rm01",
              "ObjectID": 10,
              "RegionID": 150,
              "Name": "ic_rm01"
            }
          }
        ]
      }
    },
    "NextObjectID": 61
  }
}