{
  "Parent": "base/standardbehavior",
  "Name": "base/dualcombatbehavior",
  "Properties": {
    "OutsiderMode": {
      "Flags": 4,
      "Type": 4
    },
    "ScanAlertDistance": {
      "Flags": 4,
      "Type": 3
    },
    "ScanInterval": {
      "Flags": 4,
      "Type": 3
    },
    "RangedAttackMoveStateAttack": {
      "Flags": 4,
      "Type": 5
    },
    "RangedAttackMinDelay": {
      "Flags": 4,
      "Type": 3
    },
    "RangedAttackMaxDelay": {
      "Flags": 4,
      "Type": 3
    },
    "RangedAttackMinRange": {
      "Flags": 4,
      "Type": 3
    },
    "RangedAttackMaxRange": {
      "Flags": 4,
      "Type": 3
    },
    "RangedAttackPredictTime": {
      "Flags": 4,
      "Type": 3
    },
    "RangedAttackPressure": {
      "Flags": 4,
      "Type": 3
    },
    "RangedAttackAngleDiff": {
      "Flags": 4,
      "Type": 3
    },
    "RangedLockOtherModifier": {
      "Flags": 4,
      "Type": 3
    },
    "ApproachRange": {
      "Flags": 4,
      "Type": 3
    },
    "ApproachMoveStateMove": {
      "Flags": 4,
      "Type": 5
    },
    "ApproachForceCloseRange": {
      "Flags": 4,
      "Type": 3
    },
    "ApproachForceCompleteRange": {
      "Flags": 4,
      "Type": 3
    },
    "WalkbackEnabled": {
      "Flags": 4,
      "Type": 4
    },
    "WalkbackMinRange": {
      "Flags": 4,
      "Type": 3
    },
    "WalkbackMoveStateWalkback": {
      "Flags": 4,
      "Type": 5
    },
    "WalkBackTime": {
      "Flags": 4,
      "Type": 3
    },
    "AttackMoveStateAttack": {
      "Flags": 4,
      "Type": 5
    },
    "AttackMinDelay": {
      "Flags": 4,
      "Type": 3
    },
    "AttackMaxDelay": {
      "Flags": 4,
      "Type": 3
    },
    "AttackMinRange": {
      "Flags": 4,
      "Type": 3
    },
    "AttackMaxRange": {
      "Flags": 4,
      "Type": 3
    },
    "AttackPredictTime": {
      "Flags": 4,
      "Type": 3
    },
    "AttackPressure": {
      "Flags": 4,
      "Type": 3
    },
    "StrafeEnabled": {
      "Flags": 4,
      "Type": 4
    },
    "StrafeMoveStateLeft": {
      "Flags": 4,
      "Type": 5
    },
    "StrafeMoveStateRight": {
      "Flags": 4,
      "Type": 5
    },
    "StrafeMinDuration": {
      "Flags": 4,
      "Type": 3
    },
    "StrafeMaxDuration": {
      "Flags": 4,
      "Type": 3
    },
    "StrafeMinDistance": {
      "Flags": 4,
      "Type": 3
    },
    "StrafeMaxDistance": {
      "Flags": 4,
      "Type": 3
    },
    "AnimMoveState": {
      "Flags": 4,
      "Type": 5
    },
    "TauntMoveState": {
      "Flags": 4,
      "Type": 5
    },
    "TauntMinDelay": {
      "Flags": 4,
      "Type": 3
    },
    "TauntMaxDelay": {
      "Flags": 4,
      "Type": 3
    },
    "TauntMaxAngleDiff": {
      "Flags": 4,
      "Type": 3
    },
    "FaceTargetAngleDiff": {
      "Flags": 4,
      "Type": 3
    },
    "FaceTargetMoveStateTurnLeft": {
      "Flags": 4,
      "Type": 5
    },
    "FaceTargetMoveStateTurnRight": {
      "Flags": 4,
      "Type": 5
    },
    "IdleMoveStateIdle": {
      "Flags": 4,
      "Type": 5
    },
    "IdleMinTime": {
      "Flags": 4,
      "Type": 3
    },
    "IdleMaxTime": {
      "Flags": 4,
      "Type": 3
    },
    "IdleMoveStateFidget": {
      "Flags": 4,
      "Type": 5
    },
    "IdleFidgetChance": {
      "Flags": 4,
      "Type": 3
    },
    "IdleFidgetMinTime": {
      "Flags": 4,
      "Type": 3
    },
    "IdleFidgetMaxTime": {
      "Flags": 4,
      "Type": 3
    },
    "ClearObstacleMoveState": {
      "Flags": 4,
      "Type": 5
    }
  },
  "StaticProperties": {},
  "Methods": [
    "begin",
    "onTargetUnreachable"
  ],
  "PackageName": "base",
  "DefaultValues": {
    "ApproachForceCompleteRange": -1,
    "RangedAttackMinRange": 150,
    "StrafeMoveStateRight": "StrafeRight",
    "AttackMinDelay": 1.0,
    "OutsiderMode": false,
    "IdleMinTime": 2,
    "StrafeEnabled": false,
    "RangedAttackMaxRange": 3000,
    "AttackMaxDelay": 2.0,
    "IdleFidgetChance": 0,
    "IdleFidgetMinTime": 2,
    "AttackPredictTime": 1.0,
    "StrafeMaxDistance": -1,
    "ApproachMoveStateMove": "MoveToTarget",
    "FaceTargetMoveStateTurnRight": "FaceRight",
    "TauntMoveState": "",
    "FaceTargetAngleDiff": 180,
    "RangedAttackAngleDiff": -1,
    "ID": "MinionDualCombatBehavior",
    "BackgroundActions": [
      {
        "classname": "base/scanaction",
        "properties": {
          "Position": [
            4.2459352e-30,
            3.59e-43,
            4.2459593e-30
          ]
        }
      }
    ],
    "StrafeMaxDuration": 3,
    "RangedAttackPressure": -1,
    "IdleMoveStateFidget": "",
    "RangedLockOtherModifier": 1.0,
    "RangedAttackMoveStateAttack": "RangedAttack",
    "ClearObstacleMoveState": "StandardAttack",
    "AttackPressure": -1,
    "StrafeMinDuration": 1,
    "AnimMoveState": "",
    "TauntMaxAngleDiff": 70,
    "TauntMaxDelay": 5,
    "ScanInterval": 1.5,
    "IdleMoveStateIdle": "Idle",
    "ApproachRange": 150,
    "TauntMinDelay": 5,
    "WalkbackMoveStateWalkback": "WalkBack",
    "OnAttackHandler": [],
    "PathBlockedBreakableHandler": {
      "classname": "base/animaction",
      "properties": {
        "AnimMaxAngleDiff": 180,
        "ID": "Clear Obstacle",
        "ActionCode": 5,
        "Priority": 17,
        "InterruptibleBy": [
          "Death",
          "Exit",
          "Interactive",
          "Impact"
        ],
        "Position": [
          null,
          1.734511e28,
          1.2542435e-17
        ]
      }
    },
    "FaceTargetMoveStateTurnLeft": "FaceLeft",
    "WalkbackMinRange": 100,
    "WalkBackTime": 1.0,
    "IdleMaxTime": 3,
    "StrafeMinDistance": -1,
    "RangedAttackMaxDelay": 2.0,
    "StrafeMoveStateLeft": "StrafeLeft",
    "AttackMaxRange": 150,
    "WalkbackEnabled": true,
    "ComponentActions": [
      {
        "classname": "base/rangedattackaction",
        "properties": {
          "ActionCode": 6,
          "Priority": 16,
          "InterruptibleBy": [
            "Death",
            "Interactive",
            "Impact"
          ],
          "ValidStates": [
            "Insider",
            "Outsider"
          ],
          "ResourceLock": "RangedAttack",
          "Position": [
            1.26472296e30,
            -3.1824205e21,
            3.81714e-10
          ]
        }
      },
      {
        "classname": "base/attackaction",
        "properties": {
          "ID": "Melee Attack",
          "Priority": 12,
          "InterruptibleBy": [
            "Death",
            "Interactive",
            "Impact"
          ],
          "ValidStates": [
            "Insider"
          ],
          "ResourceLock": "Attack",
          "Position": [
            9.47e-42,
            0.0,
            1.1225476e33
          ]
        }
      },
      {
        "classname": "base/approachaction",
        "properties": {
          "ID": "Approach Target",
          "Priority": 8,
          "InterruptibleBy": [
            "ANY"
          ],
          "Position": [
            1e-45,
            0.0,
            9.36e-42
          ]
        }
      },
      {
        "classname": "base/walkbackaction",
        "properties": {
          "ID": "Walkback",
          "ActionCode": 3,
          "Priority": 4,
          "Chance": 0.65,
          "InterruptibleBy": [
            "ANY"
          ],
          "Position": [
            1.3099586e-29,
            3.59e-43,
            1e-45
          ]
        }
      },
      {
        "classname": "base/strafeaction",
        "properties": {
          "ID": "Strafe",
          "ActionCode": 4,
          "Priority": 3,
          "Chance": 0.55,
          "InterruptibleBy": [
            "ANY",
            "Impact"
          ],
          "Position": [
            8.186e-42,
            0.0,
            0.012519244
          ]
        }
      },
      {
        "classname": "base/animaction",
        "properties": {
          "ID": "Taunt",
          "ActionCode": 2,
          "Priority": 2,
          "Chance": 0.9,
          "InterruptibleBy": [
            "Death",
            "Interactive",
            "Impact"
          ],
          "ResourceLock": "Taunt",
          "Position": [
            8.235e-42,
            0.0,
            7.44514e-22
          ]
        }
      },
      {
        "classname": "base/facetargetaction",
        "properties": {
          "ID": "Face Target",
          "Priority": 1,
          "InterruptibleBy": [
            "Death",
            "Interactive",
            "Impact"
          ],
          "Position": [
            1.3092363e-29,
            3.59e-43,
            1e-45
          ]
        }
      },
      {
        "classname": "base/idleaction",
        "properties": {
          "ID": "Idle",
          "ActionCode": 1,
          "Priority": 1,
          "InterruptibleBy": [
            "ANY"
          ],
          "Position": [
            7.875489e-16,
            -3.9190243e-33,
            1.2388159e-29
          ]
        }
      }
    ],
    "ApproachForceCloseRange": -1,
    "AttackMoveStateAttack": "StandardAttack",
    "IdleFidgetMaxTime": 4,
    "RangedAttackPredictTime": 0.0,
    "RangedAttackMinDelay": 1.0,
    "ScanAlertDistance": -1,
    "AttackMinRange": 0
  },
  "States": {
    "Outsider": {
      "methods": [
        "getCurrentState"
      ]
    },
    "Insider": {
      "methods": [
        "getCurrentState"
      ]
    },
    "LostTarget": {
      "methods": [
        "onEnter"
      ]
    }
  }
}